bbl/__init__.py
bbl/apps.py
bbl/bricks.py
bbl/components.py
bbl-0.1.0.dist-info/WHEEL
bbl-0.1.0.dist-info/METADATA
bbl-0.1.0.dist-info/RECORD
